launcherctl/__init__.py
launcherctl/_app.py
launcherctl/_launcher.py
launcherctl/_util.py
launcherctl-1.0.1.dist-info/LICENSE
launcherctl-1.0.1.dist-info/METADATA
launcherctl-1.0.1.dist-info/WHEEL
launcherctl-1.0.1.dist-info/top_level.txt
launcherctl-1.0.1.dist-info/RECORD
