Metadata-Version: 2.1
Name: launcherctl
Version: 1.0.1
Summary: Python wrapper around launcherctl.
Author-email: Nathaniel van Diepen <eeems@eeems.email>
Maintainer-email: Nathaniel van Diepen <eeems@eeems.email>
Project-URL: Homepage, https://github.com/Eeems-Org/python-launcherctl
Project-URL: Repository, https://github.com/Eeems-Org/python-launcherctl.git
Project-URL: Issues, https://github.com/Eeems-Org/python-launcherctl/issues
Classifier: Intended Audience :: Developers
Classifier: Topic :: Software Development :: Libraries
Classifier: License :: OSI Approved :: MIT License
Classifier: Programming Language :: Python :: 3.11
Classifier: Programming Language :: Python :: 3.12
Requires-Python: >=3.11
License-File: LICENSE
